[
    {
        "DIA": "2026-02-21",
        "HORARIO": "10h40min",
        "LOCAL": "Palestra",
        "GRUPO": "A",
        "Mandante": "UNIFESP Osasco",
        "PLACAR": "05X04",
        "Visitante": "IBMEC",
        "GOLS_MANDANTE": "05",
        "GOLS_VISITANTE": "04",
        "ID": "ef4e97e3-5af2-4124-a6e6-1768c0ed6d73",
        "SIMULADOR": false
    },
    {
        "DIA": "2026-02-21",
        "HORARIO": "14h40min",
        "LOCAL": "Palestra",
        "GRUPO": "A",
        "Mandante": "Medicina São Camilo",
        "PLACAR": "03X04",
        "Visitante": "Medicina São Bernardo",
        "GOLS_MANDANTE": "03",
        "GOLS_VISITANTE": "04",
        "ID": "53055453-a2a1-474a-a57b-64452b1d3408",
        "SIMULADOR": false
    },
    {
        "DIA": "2026-02-21",
        "HORARIO": "16h",
        "LOCAL": "Palestra",
        "GRUPO": "B",
        "Mandante": "Engenharia Mackenzie",
        "PLACAR": "05X02",
        "Visitante": "IME USP",
        "GOLS_MANDANTE": "05",
        "GOLS_VISITANTE": "02",
        "ID": "9e13bd97-33ae-4ae2-b7e6-e0f062e7dc6f",
        "SIMULADOR": false
    },
    {
        "DIA": "2026-02-21",
        "HORARIO": "17h20min",
        "LOCAL": "Palestra",
        "GRUPO": "B",
        "Mandante": "FEA PUC",
        "PLACAR": "07X01",
        "Visitante": "Medicina Paulista",
        "GOLS_MANDANTE": "07",
        "GOLS_VISITANTE": "01",
        "ID": "b038a289-e91f-48ad-a080-27b097ac1785",
        "SIMULADOR": false
    },
    {
        "DIA": "2026-02-28",
        "HORARIO": "10h40 min",
        "LOCAL": "Palestra",
        "GRUPO": "A",
        "Mandante": "FFLCH USP",
        "PLACAR": "03X03",
        "Visitante": "Cásper Líbero",
        "GOLS_MANDANTE": "03",
        "GOLS_VISITANTE": "03",
        "ID": "9ff43246-19a4-41b7-a92b-0702ef961718",
        "SIMULADOR": false
    },
    {
        "DIA": "2026-02-28",
        "HORARIO": "14h40min",
        "LOCAL": "Palestra",
        "GRUPO": "B",
        "Mandante": "Medicina Taubaté",
        "PLACAR": "01X03",
        "Visitante": "Medicina USP",
        "GOLS_MANDANTE": "01",
        "GOLS_VISITANTE": "03",
        "ID": "0853614b-daba-4439-aa4e-764694c2e5ca",
        "SIMULADOR": false
    },
    {
        "DIA": "2026-03-14",
        "HORARIO": "08 h",
        "LOCAL": "Palestra",
        "GRUPO": "A",
        "Mandante": "Cásper Líbero",
        "PLACAR": "02X01",
        "Visitante": "UNIFESP Osasco",
        "GOLS_MANDANTE": "02",
        "GOLS_VISITANTE": "01",
        "ID": "eb7427e7-8fc0-427c-b292-ce2b02d35070",
        "SIMULADOR": false
    },
    {
        "DIA": "2026-03-14",
        "HORARIO": "09h20min",
        "LOCAL": "Idalina",
        "GRUPO": "A",
        "Mandante": "IBMEC",
        "PLACAR": "02X04",
        "Visitante": "Medicina São Camilo",
        "GOLS_MANDANTE": "02",
        "GOLS_VISITANTE": "04",
        "ID": "7961dcbd-a480-484e-b7d6-edd38e8c2920",
        "SIMULADOR": false
    },
    {
        "DIA": "2026-03-14",
        "HORARIO": "10h40min",
        "LOCAL": "Idalina",
        "GRUPO": "B",
        "Mandante": "IME USP",
        "PLACAR": "01X01",
        "Visitante": "Medicina Taubaté",
        "GOLS_MANDANTE": "01",
        "GOLS_VISITANTE": "01",
        "ID": "5266e605-d34c-4c88-baa0-c1264edb5132",
        "SIMULADOR": false
    },
    {
        "DIA": "2026-03-14",
        "HORARIO": "14h40min",
        "LOCAL": "Palestra",
        "GRUPO": "B",
        "Mandante": "FEA PUC",
        "PLACAR": "01X01",
        "Visitante": "Medicina USP",
        "GOLS_MANDANTE": "01",
        "GOLS_VISITANTE": "01",
        "ID": "efbf59e3-075c-4d9a-95d3-a5b5cdb0c4ce",
        "SIMULADOR": false
    },
    {
        "DIA": "2026-03-15",
        "HORARIO": "09h20 min",
        "LOCAL": "Palestra",
        "GRUPO": "A",
        "Mandante": "Medicina São Bernardo",
        "PLACAR": "05X03",
        "Visitante": "FFLCH USP",
        "GOLS_MANDANTE": "05",
        "GOLS_VISITANTE": "03",
        "ID": "fab923b1-31e3-48c6-8afc-837908e012c0",
        "SIMULADOR": false
    },
    {
        "DIA": "2026-03-15",
        "HORARIO": "13h20min",
        "LOCAL": "Palestra",
        "GRUPO": "B",
        "Mandante": "Medicina Paulista",
        "PLACAR": "00X06",
        "Visitante": "Engenharia Mackenzie",
        "GOLS_MANDANTE": "00",
        "GOLS_VISITANTE": "06",
        "ID": "d69296d2-db4f-49a1-ae99-b284987b1620",
        "SIMULADOR": false
    },
    {
        "DIA": "2026-03-21",
        "HORARIO": "08 h",
        "LOCAL": "Idalina",
        "GRUPO": "B",
        "Mandante": "IME USP",
        "PLACAR": "02X04",
        "Visitante": "FEA PUC",
        "GOLS_MANDANTE": "02",
        "GOLS_VISITANTE": "04",
        "ID": "38752068-fad8-40ea-9a2a-bf76235105df",
        "SIMULADOR": false
    },
    {
        "DIA": "2026-03-21",
        "HORARIO": "09h20min",
        "LOCAL": "Palestra",
        "GRUPO": "A",
        "Mandante": "IBMEC",
        "PLACAR": "04X01",
        "Visitante": "Cásper Líbero",
        "GOLS_MANDANTE": "04",
        "GOLS_VISITANTE": "01",
        "ID": "b8c93e1d-f970-4ce2-b6ea-7acbeba9e7a9",
        "SIMULADOR": false
    },
    {
        "DIA": "2026-03-22",
        "HORARIO": "09h20 min",
        "LOCAL": "Palestra",
        "GRUPO": "B",
        "Mandante": "Medicina Taubaté",
        "PLACAR": "01X02",
        "Visitante": "Engenharia Mackenzie",
        "GOLS_MANDANTE": "01",
        "GOLS_VISITANTE": "02",
        "ID": "d1fb1a67-3189-41b5-a270-7c1097dbd274",
        "SIMULADOR": false
    },
    {
        "DIA": "2026-03-28",
        "HORARIO": "09 h",
        "LOCAL": "SEMEF",
        "GRUPO": "B",
        "Mandante": "Medicina USP",
        "PLACAR": "X",
        "Visitante": "Medicina Paulista",
        "GOLS_MANDANTE": "",
        "GOLS_VISITANTE": "",
        "ID": "bf328bbf-d3c6-4155-bd9f-a4fa67d28421",
        "SIMULADOR": true
    },
    {
        "DIA": "2026-03-28",
        "HORARIO": "10h20min",
        "LOCAL": "SEMEF",
        "GRUPO": "A",
        "Mandante": "FFLCH USP",
        "PLACAR": "X",
        "Visitante": "Medicina São Camilo",
        "GOLS_MANDANTE": "",
        "GOLS_VISITANTE": "",
        "ID": "0cffd99c-c9a6-449e-b67c-9f8ff97ce20b",
        "SIMULADOR": true
    },
    {
        "DIA": "2026-03-28",
        "HORARIO": "15h50min",
        "LOCAL": "Idalina",
        "GRUPO": "A",
        "Mandante": "Medicina São Bernardo",
        "PLACAR": "X",
        "Visitante": "UNIFESP Osasco",
        "GOLS_MANDANTE": "",
        "GOLS_VISITANTE": "",
        "ID": "643a1368-fff9-456e-9db4-5037fd4913c1",
        "SIMULADOR": true
    },
    {
        "DIA": null,
        "HORARIO": null,
        "LOCAL": null,
        "GRUPO": "A",
        "Mandante": "Cásper Líbero",
        "PLACAR": "X",
        "Visitante": "Medicina São Bernardo",
        "GOLS_MANDANTE": "",
        "GOLS_VISITANTE": "",
        "ID": "70d4630d-7c82-48b1-9eb6-8db85672e470",
        "SIMULADOR": true
    },
    {
        "DIA": null,
        "HORARIO": null,
        "LOCAL": null,
        "GRUPO": "A",
        "Mandante": "FFLCH USP",
        "PLACAR": "X",
        "Visitante": "IBMEC",
        "GOLS_MANDANTE": "",
        "GOLS_VISITANTE": "",
        "ID": "d934839d-a549-4ceb-950a-d41b02edfff9",
        "SIMULADOR": true
    },
    {
        "DIA": null,
        "HORARIO": null,
        "LOCAL": null,
        "GRUPO": "A",
        "Mandante": "Medicina São Camilo",
        "PLACAR": "X",
        "Visitante": "UNIFESP Osasco",
        "GOLS_MANDANTE": "",
        "GOLS_VISITANTE": "",
        "ID": "d7d6344d-cff6-42fa-8ff6-789139505eb6",
        "SIMULADOR": true
    },
    {
        "DIA": null,
        "HORARIO": null,
        "LOCAL": null,
        "GRUPO": "A",
        "Mandante": "Cásper Líbero",
        "PLACAR": "X",
        "Visitante": "Medicina São Camilo",
        "GOLS_MANDANTE": "",
        "GOLS_VISITANTE": "",
        "ID": "24c09786-8b3f-41c0-9fa1-16739d5165fd",
        "SIMULADOR": true
    },
    {
        "DIA": null,
        "HORARIO": null,
        "LOCAL": null,
        "GRUPO": "A",
        "Mandante": "UNIFESP Osasco",
        "PLACAR": "X",
        "Visitante": "FFLCH USP",
        "GOLS_MANDANTE": "",
        "GOLS_VISITANTE": "",
        "ID": "7c993146-7ca3-4b79-9b93-ff5b8e3d945b",
        "SIMULADOR": true
    },
    {
        "DIA": null,
        "HORARIO": null,
        "LOCAL": null,
        "GRUPO": "A",
        "Mandante": "IBMEC",
        "PLACAR": "X",
        "Visitante": "Medicina São Bernardo",
        "GOLS_MANDANTE": "",
        "GOLS_VISITANTE": "",
        "ID": "11eebe08-3dff-451e-9bf7-f8d7d47a52da",
        "SIMULADOR": true
    },
    {
        "DIA": null,
        "HORARIO": null,
        "LOCAL": null,
        "GRUPO": "B",
        "Mandante": "Medicina USP",
        "PLACAR": "X",
        "Visitante": "IME USP",
        "GOLS_MANDANTE": "",
        "GOLS_VISITANTE": "",
        "ID": "bb4b72fa-bbe3-4542-9348-99f8d50f62f8",
        "SIMULADOR": true
    },
    {
        "DIA": null,
        "HORARIO": null,
        "LOCAL": null,
        "GRUPO": "B",
        "Mandante": "Medicina Taubaté",
        "PLACAR": "X",
        "Visitante": "Medicina Paulista",
        "GOLS_MANDANTE": "",
        "GOLS_VISITANTE": "",
        "ID": "7ae73e15-a837-46df-9153-031a6c0619f8",
        "SIMULADOR": true
    },
    {
        "DIA": null,
        "HORARIO": null,
        "LOCAL": null,
        "GRUPO": "B",
        "Mandante": "Engenharia Mackenzie",
        "PLACAR": "X",
        "Visitante": "FEA PUC",
        "GOLS_MANDANTE": "",
        "GOLS_VISITANTE": "",
        "ID": "0587fc1c-d732-49c4-b12f-722e41943169",
        "SIMULADOR": true
    },
    {
        "DIA": null,
        "HORARIO": null,
        "LOCAL": null,
        "GRUPO": "B",
        "Mandante": "Medicina USP",
        "PLACAR": "X",
        "Visitante": "Engenharia Mackenzie",
        "GOLS_MANDANTE": "",
        "GOLS_VISITANTE": "",
        "ID": "19dbc8bf-177b-4b61-b0ae-f154116a2739",
        "SIMULADOR": true
    },
    {
        "DIA": null,
        "HORARIO": null,
        "LOCAL": null,
        "GRUPO": "B",
        "Mandante": "FEA PUC",
        "PLACAR": "X",
        "Visitante": "Medicina Taubaté",
        "GOLS_MANDANTE": "",
        "GOLS_VISITANTE": "",
        "ID": "a8c907e2-ff13-4fb7-a74d-1e76749a0940",
        "SIMULADOR": true
    },
    {
        "DIA": null,
        "HORARIO": null,
        "LOCAL": null,
        "GRUPO": "B",
        "Mandante": "Medicina Paulista",
        "PLACAR": "X",
        "Visitante": "IME USP",
        "GOLS_MANDANTE": "",
        "GOLS_VISITANTE": "",
        "ID": "214d6ff4-3ad0-4714-b01b-4e646da4d85f",
        "SIMULADOR": true
    }
]